griffe_modernized_annotations/__init__.py
griffe_modernized_annotations/extension.py
griffe_modernized_annotations/modernizer.py
griffe_modernized_annotations/predicates.py
griffe_modernized_annotations/py.typed
griffe_modernized_annotations/transforms.py
griffe_modernized_annotations/traversal.py
griffe_modernized_annotations/types.py
griffe_modernized_annotations/utils.py
griffe_modernized_annotations/proposals/__init__.py
griffe_modernized_annotations/proposals/pep.py
griffe_modernized_annotations/proposals/pep585.py
griffe_modernized_annotations/proposals/pep604.py
tests/__init__.py
tests/conftest.py
tests/test_extension.py
tests/utils.py
griffe_modernized_annotations-1.0.8.dist-info/LICENSE
griffe_modernized_annotations-1.0.8.dist-info/METADATA
griffe_modernized_annotations-1.0.8.dist-info/WHEEL
griffe_modernized_annotations-1.0.8.dist-info/top_level.txt
griffe_modernized_annotations-1.0.8.dist-info/RECORD
